{
	"output": [
		{
			"css": true,
			"full": false,
			"reset": true,
			"background-colors": true,
			"text-colors": true,
			"custom-properties": true,
			"ease-classes": false,
			"button-default": true,
			"button-colors": true,
			"button-sizes": true,
			"button-rounded": true,
			"button-round": true,
			"button-icons": true,
			"button-text-transform": true,
			"button-rotated": true,
			"button-border": true,
			"custom-properties-media-queries": false,
			"custom-properties-colors": false,
			"grid": true,
			"grid-helpers": false,
			"grid-hide-show-classes": false,
			"grid-only-classes": true,
			"grid-counted-columns": true,
			"grid-parts": true,
			"grid-offset": false,
			"grid-push": false,
			"grid-pull": false,
			"grid-non-breaking-column": false,
			"grid-columns": true,
			"grid-cssgrid": false,
			"grid-row-breakpoints": true
		}
	]
}
